cmsplugin_alerts/__init__.py
cmsplugin_alerts/alert.py
cmsplugin_alerts/cms_config.py
cmsplugin_alerts/cms_toolbar.py
cmsplugin_alerts/models.py
cmsplugin_alerts/templates/cmsplugin_alerts/alert/email_page_published_alert.txt
cmsplugin_alerts/templates/cmsplugin_alerts/alert/page_published_alert.html
cmsplugin_alerts-2.0.0.dist-info/LICENSE
cmsplugin_alerts-2.0.0.dist-info/METADATA
cmsplugin_alerts-2.0.0.dist-info/WHEEL
cmsplugin_alerts-2.0.0.dist-info/top_level.txt
cmsplugin_alerts-2.0.0.dist-info/RECORD
